{"metadata": {"dbt_schema_version": "https://schemas.getdbt.com/dbt/run-results/v4.json", "dbt_version": "1.3.0", "generated_at": "2022-10-28T17:24:47.719415Z", "invocation_id": "ff87a44a-134b-466d-9520-8523805c3bae", "env": {}}, "results": [{"status": "success", "timing": [{"name": "compile", "started_at": "2022-10-28T17:24:41.001585Z", "completed_at": "2022-10-28T17:24:41.015239Z"}, {"name": "execute", "started_at": "2022-10-28T17:24:41.016711Z", "completed_at": "2022-10-28T17:24:41.016736Z"}], "thread_id": "Thread-1", "execution_time": 0.020357131958007812, "adapter_response": {}, "message": null, "failures": null, "unique_id": "seed.facebook_pages_integration_tests.facebook_pages_daily_page_metrics_total_data"}, {"status": "success", "timing": [{"name": "compile", "started_at": "2022-10-28T17:24:41.001794Z", "completed_at": "2022-10-28T17:24:41.015445Z"}, {"name": "execute", "started_at": "2022-10-28T17:24:41.016833Z", "completed_at": "2022-10-28T17:24:41.016837Z"}], "thread_id": "Thread-2", "execution_time": 0.019527912139892578, "adapter_response": {}, "message": null, "failures": null, "unique_id": "seed.facebook_pages_integration_tests.facebook_pages_lifetime_post_metrics_total_data"}, {"status": "success", "timing": [{"name": "compile", "started_at": "2022-10-28T17:24:41.001952Z", "completed_at": "2022-10-28T17:24:41.015612Z"}, {"name": "execute", "started_at": "2022-10-28T17:24:41.016928Z", "completed_at": "2022-10-28T17:24:41.016932Z"}], "thread_id": "Thread-3", "execution_time": 0.018763065338134766, "adapter_response": {}, "message": null, "failures": null, "unique_id": "seed.facebook_pages_integration_tests.facebook_pages_page_data"}, {"status": "success", "timing": [{"name": "compile", "started_at": "2022-10-28T17:24:41.002094Z", "completed_at": "2022-10-28T17:24:41.015769Z"}, {"name": "execute", "started_at": "2022-10-28T17:24:41.017011Z", "completed_at": "2022-10-28T17:24:41.017015Z"}], "thread_id": "Thread-4", "execution_time": 0.018205881118774414, "adapter_response": {}, "message": null, "failures": null, "unique_id": "seed.facebook_pages_integration_tests.facebook_pages_post_history_data"}, {"status": "success", "timing": [{"name": "compile", "started_at": "2022-10-28T17:24:41.022068Z", "completed_at": "2022-10-28T17:24:41.059916Z"}, {"name": "execute", "started_at": "2022-10-28T17:24:41.060672Z", "completed_at": "2022-10-28T17:24:41.060681Z"}], "thread_id": "Thread-2", "execution_time": 0.04178476333618164, "adapter_response": {}, "message": null, "failures": null, "unique_id": "model.facebook_pages_source.stg_facebook_pages__daily_page_metrics_total_tmp"}, {"status": "success", "timing": [{"name": "compile", "started_at": "2022-10-28T17:24:41.022332Z", "completed_at": "2022-10-28T17:24:41.060127Z"}, {"name": "execute", "started_at": "2022-10-28T17:24:41.060880Z", "completed_at": "2022-10-28T17:24:41.060884Z"}], "thread_id": "Thread-1", "execution_time": 0.04171395301818848, "adapter_response": {}, "message": null, "failures": null, "unique_id": "model.facebook_pages_source.stg_facebook_pages__lifetime_post_metrics_total_tmp"}, {"status": "success", "timing": [{"name": "compile", "started_at": "2022-10-28T17:24:41.046617Z", "completed_at": "2022-10-28T17:24:41.060419Z"}, {"name": "execute", "started_at": "2022-10-28T17:24:41.061567Z", "completed_at": "2022-10-28T17:24:41.061572Z"}], "thread_id": "Thread-3", "execution_time": 0.04183340072631836, "adapter_response": {}, "message": null, "failures": null, "unique_id": "model.facebook_pages_source.stg_facebook_pages__page_tmp"}, {"status": "success", "timing": [{"name": "compile", "started_at": "2022-10-28T17:24:41.050996Z", "completed_at": "2022-10-28T17:24:41.060578Z"}, {"name": "execute", "started_at": "2022-10-28T17:24:41.062084Z", "completed_at": "2022-10-28T17:24:41.062088Z"}], "thread_id": "Thread-4", "execution_time": 0.041882991790771484, "adapter_response": {}, "message": null, "failures": null, "unique_id": "model.facebook_pages_source.stg_facebook_pages__post_history_tmp"}, {"status": "success", "timing": [{"name": "compile", "started_at": "2022-10-28T17:24:41.078903Z", "completed_at": "2022-10-28T17:24:42.675270Z"}, {"name": "execute", "started_at": "2022-10-28T17:24:42.675595Z", "completed_at": "2022-10-28T17:24:42.675599Z"}], "thread_id": "Thread-3", "execution_time": 1.7491867542266846, "adapter_response": {}, "message": null, "failures": null, "unique_id": "model.facebook_pages_source.stg_facebook_pages__page"}, {"status": "success", "timing": [{"name": "compile", "started_at": "2022-10-28T17:24:41.065383Z", "completed_at": "2022-10-28T17:24:42.674822Z"}, {"name": "execute", "started_at": "2022-10-28T17:24:42.675071Z", "completed_at": "2022-10-28T17:24:42.675082Z"}], "thread_id": "Thread-1", "execution_time": 1.7510402202606201, "adapter_response": {}, "message": null, "failures": null, "unique_id": "model.facebook_pages_source.stg_facebook_pages__lifetime_post_metrics_total"}, {"status": "success", "timing": [{"name": "compile", "started_at": "2022-10-28T17:24:41.079005Z", "completed_at": "2022-10-28T17:24:42.675357Z"}, {"name": "execute", "started_at": "2022-10-28T17:24:42.675674Z", "completed_at": "2022-10-28T17:24:42.675679Z"}], "thread_id": "Thread-4", "execution_time": 1.750737190246582, "adapter_response": {}, "message": null, "failures": null, "unique_id": "model.facebook_pages_source.stg_facebook_pages__post_history"}, {"status": "success", "timing": [{"name": "compile", "started_at": "2022-10-28T17:24:42.819120Z", "completed_at": "2022-10-28T17:24:42.852156Z"}, {"name": "execute", "started_at": "2022-10-28T17:24:42.852791Z", "completed_at": "2022-10-28T17:24:42.852800Z"}], "thread_id": "Thread-3", "execution_time": 0.03612780570983887, "adapter_response": {}, "message": null, "failures": null, "unique_id": "test.facebook_pages_source.dbt_utils_unique_combination_of_columns_stg_facebook_pages__lifetime_post_metrics_total_post_id__date_day__source_relation.c12787b228"}, {"status": "success", "timing": [{"name": "compile", "started_at": "2022-10-28T17:24:42.819265Z", "completed_at": "2022-10-28T17:24:42.852278Z"}, {"name": "execute", "started_at": "2022-10-28T17:24:42.852893Z", "completed_at": "2022-10-28T17:24:42.852897Z"}], "thread_id": "Thread-4", "execution_time": 0.036077022552490234, "adapter_response": {}, "message": null, "failures": null, "unique_id": "test.facebook_pages_source.dbt_utils_unique_combination_of_columns_stg_facebook_pages__page_page_id__source_relation.32a7459a05"}, {"status": "success", "timing": [{"name": "compile", "started_at": "2022-10-28T17:24:42.819413Z", "completed_at": "2022-10-28T17:24:42.852371Z"}, {"name": "execute", "started_at": "2022-10-28T17:24:42.852990Z", "completed_at": "2022-10-28T17:24:42.852993Z"}], "thread_id": "Thread-1", "execution_time": 0.0361180305480957, "adapter_response": {}, "message": null, "failures": null, "unique_id": "test.facebook_pages_source.not_null_stg_facebook_pages__lifetime_post_metrics_total_date_day.de0419d721"}, {"status": "success", "timing": [{"name": "compile", "started_at": "2022-10-28T17:24:42.856441Z", "completed_at": "2022-10-28T17:24:42.866481Z"}, {"name": "execute", "started_at": "2022-10-28T17:24:42.866947Z", "completed_at": "2022-10-28T17:24:42.866953Z"}], "thread_id": "Thread-3", "execution_time": 0.012232065200805664, "adapter_response": {}, "message": null, "failures": null, "unique_id": "test.facebook_pages_source.not_null_stg_facebook_pages__lifetime_post_metrics_total_post_id.66563712ec"}, {"status": "success", "timing": [{"name": "compile", "started_at": "2022-10-28T17:24:42.856527Z", "completed_at": "2022-10-28T17:24:42.866585Z"}, {"name": "execute", "started_at": "2022-10-28T17:24:42.867118Z", "completed_at": "2022-10-28T17:24:42.867121Z"}], "thread_id": "Thread-4", "execution_time": 0.012328147888183594, "adapter_response": {}, "message": null, "failures": null, "unique_id": "test.facebook_pages_source.not_null_stg_facebook_pages__page_page_id.3839292889"}, {"status": "success", "timing": [{"name": "compile", "started_at": "2022-10-28T17:24:42.856608Z", "completed_at": "2022-10-28T17:24:42.866766Z"}, {"name": "execute", "started_at": "2022-10-28T17:24:42.867581Z", "completed_at": "2022-10-28T17:24:42.867585Z"}], "thread_id": "Thread-1", "execution_time": 0.012497901916503906, "adapter_response": {}, "message": null, "failures": null, "unique_id": "model.facebook_pages.int_facebook_pages__lastest_post"}, {"status": "success", "timing": [{"name": "compile", "started_at": "2022-10-28T17:24:42.869894Z", "completed_at": "2022-10-28T17:24:42.881658Z"}, {"name": "execute", "started_at": "2022-10-28T17:24:42.881845Z", "completed_at": "2022-10-28T17:24:42.881851Z"}], "thread_id": "Thread-3", "execution_time": 0.01347970962524414, "adapter_response": {}, "message": null, "failures": null, "unique_id": "test.facebook_pages_source.dbt_utils_unique_combination_of_columns_stg_facebook_pages__post_history_post_id__updated_timestamp__source_relation.67de991272"}, {"status": "success", "timing": [{"name": "compile", "started_at": "2022-10-28T17:24:42.870059Z", "completed_at": "2022-10-28T17:24:42.882351Z"}, {"name": "execute", "started_at": "2022-10-28T17:24:42.882536Z", "completed_at": "2022-10-28T17:24:42.882540Z"}], "thread_id": "Thread-4", "execution_time": 0.013691186904907227, "adapter_response": {}, "message": null, "failures": null, "unique_id": "test.facebook_pages_source.not_null_stg_facebook_pages__post_history_post_id.fd3293856c"}, {"status": "success", "timing": [{"name": "compile", "started_at": "2022-10-28T17:24:42.874396Z", "completed_at": "2022-10-28T17:24:42.882977Z"}, {"name": "execute", "started_at": "2022-10-28T17:24:42.883129Z", "completed_at": "2022-10-28T17:24:42.883133Z"}], "thread_id": "Thread-1", "execution_time": 0.013872861862182617, "adapter_response": {}, "message": null, "failures": null, "unique_id": "model.facebook_pages.facebook_pages__posts_report"}, {"status": "success", "timing": [{"name": "compile", "started_at": "2022-10-28T17:24:42.884718Z", "completed_at": "2022-10-28T17:24:42.891635Z"}, {"name": "execute", "started_at": "2022-10-28T17:24:42.891812Z", "completed_at": "2022-10-28T17:24:42.891818Z"}], "thread_id": "Thread-4", "execution_time": 0.007953882217407227, "adapter_response": {}, "message": null, "failures": null, "unique_id": "test.facebook_pages.not_null_facebook_pages__posts_report_date_day.ec0cb997b7"}, {"status": "success", "timing": [{"name": "compile", "started_at": "2022-10-28T17:24:42.884634Z", "completed_at": "2022-10-28T17:24:42.892222Z"}, {"name": "execute", "started_at": "2022-10-28T17:24:42.892461Z", "completed_at": "2022-10-28T17:24:42.892464Z"}], "thread_id": "Thread-3", "execution_time": 0.008855104446411133, "adapter_response": {}, "message": null, "failures": null, "unique_id": "test.facebook_pages.dbt_utils_unique_combination_of_columns_facebook_pages__posts_report_post_id__date_day__source_relation.19483d54fa"}, {"status": "success", "timing": [{"name": "compile", "started_at": "2022-10-28T17:24:41.065290Z", "completed_at": "2022-10-28T17:24:47.513142Z"}, {"name": "execute", "started_at": "2022-10-28T17:24:47.513436Z", "completed_at": "2022-10-28T17:24:47.513448Z"}], "thread_id": "Thread-2", "execution_time": 6.570188045501709, "adapter_response": {}, "message": null, "failures": null, "unique_id": "model.facebook_pages_source.stg_facebook_pages__daily_page_metrics_total"}, {"status": "success", "timing": [{"name": "compile", "started_at": "2022-10-28T17:24:47.636745Z", "completed_at": "2022-10-28T17:24:47.650157Z"}, {"name": "execute", "started_at": "2022-10-28T17:24:47.661046Z", "completed_at": "2022-10-28T17:24:47.661056Z"}], "thread_id": "Thread-1", "execution_time": 0.02620100975036621, "adapter_response": {}, "message": null, "failures": null, "unique_id": "model.facebook_pages.facebook_pages__pages_report"}, {"status": "success", "timing": [{"name": "compile", "started_at": "2022-10-28T17:24:47.645882Z", "completed_at": "2022-10-28T17:24:47.650631Z"}, {"name": "execute", "started_at": "2022-10-28T17:24:47.661626Z", "completed_at": "2022-10-28T17:24:47.661643Z"}], "thread_id": "Thread-3", "execution_time": 0.018650293350219727, "adapter_response": {}, "message": null, "failures": null, "unique_id": "test.facebook_pages_source.not_null_stg_facebook_pages__daily_page_metrics_total_date_day.880eb929d5"}, {"status": "success", "timing": [{"name": "compile", "started_at": "2022-10-28T17:24:47.650376Z", "completed_at": "2022-10-28T17:24:47.661817Z"}, {"name": "execute", "started_at": "2022-10-28T17:24:47.663775Z", "completed_at": "2022-10-28T17:24:47.663787Z"}], "thread_id": "Thread-4", "execution_time": 0.02722311019897461, "adapter_response": {}, "message": null, "failures": null, "unique_id": "test.facebook_pages_source.dbt_utils_unique_combination_of_columns_stg_facebook_pages__daily_page_metrics_total_page_id__date_day__source_relation.b90aa3f043"}, {"status": "success", "timing": [{"name": "compile", "started_at": "2022-10-28T17:24:47.650523Z", "completed_at": "2022-10-28T17:24:47.662446Z"}, {"name": "execute", "started_at": "2022-10-28T17:24:47.664355Z", "completed_at": "2022-10-28T17:24:47.664362Z"}], "thread_id": "Thread-2", "execution_time": 0.02113199234008789, "adapter_response": {}, "message": null, "failures": null, "unique_id": "test.facebook_pages_source.not_null_stg_facebook_pages__daily_page_metrics_total_page_id.937414eaf3"}, {"status": "success", "timing": [{"name": "compile", "started_at": "2022-10-28T17:24:47.666730Z", "completed_at": "2022-10-28T17:24:47.715262Z"}, {"name": "execute", "started_at": "2022-10-28T17:24:47.715963Z", "completed_at": "2022-10-28T17:24:47.715973Z"}], "thread_id": "Thread-3", "execution_time": 0.05198931694030762, "adapter_response": {}, "message": null, "failures": null, "unique_id": "test.facebook_pages.not_null_facebook_pages__pages_report_date_day.0d88b4b154"}, {"status": "success", "timing": [{"name": "compile", "started_at": "2022-10-28T17:24:47.666492Z", "completed_at": "2022-10-28T17:24:47.715394Z"}, {"name": "execute", "started_at": "2022-10-28T17:24:47.716163Z", "completed_at": "2022-10-28T17:24:47.716167Z"}], "thread_id": "Thread-1", "execution_time": 0.05325579643249512, "adapter_response": {}, "message": null, "failures": null, "unique_id": "test.facebook_pages.dbt_utils_unique_combination_of_columns_facebook_pages__pages_report_page_id__date_day__source_relation.f6275f55a9"}, {"status": "success", "timing": [{"name": "compile", "started_at": "2022-10-28T17:24:47.711447Z", "completed_at": "2022-10-28T17:24:47.715583Z"}, {"name": "execute", "started_at": "2022-10-28T17:24:47.716728Z", "completed_at": "2022-10-28T17:24:47.716732Z"}], "thread_id": "Thread-4", "execution_time": 0.05101609230041504, "adapter_response": {}, "message": null, "failures": null, "unique_id": "test.facebook_pages.not_null_facebook_pages__pages_report_page_id.42b740bfbe"}], "elapsed_time": 10.759577989578247, "args": {"write_json": true, "use_colors": true, "printer_width": 80, "version_check": true, "partial_parse": true, "static_parser": true, "profiles_dir": "/Users/avinash.kunnath/.dbt", "send_anonymous_usage_stats": true, "event_buffer_size": 100000, "quiet": false, "no_print": false, "target": "postgres", "compile": true, "which": "generate", "rpc_method": "docs.generate", "indirect_selection": "eager"}}